[{"type":"text","html":"<div> <font style=\"font-family: Arial;\" size=\"2\">Món miến xào này màu sắc rất sinh động hấp dẫn.Miến xào làm đơn giản chỉ hơi cầu kỳ khâu chuẩn bị nguyên liệu chút thôi.</font> </div><font>Món miến xào này màu sắc rất sinh động hấp dẫn.Miến xào làm đơn giản chỉ hơi cầu kỳ khâu chuẩn bị nguyên liệu chút thôi.</font><div>Nguyên liệu</div><div> <font><span><span><ul><li>- 100g miến</li><li>- 100g thịt bò</li><li>- Vài cái nấm rơm</li><li>- ½ củ cà rốt</li><li>- ½ củ hành tây</li><li>- ½ quả dưa chuột hoặc bí ngòi</li><li>- 1 quả trứng</li><li>- 1 thìa tỏi băm</li><li>- 1 ít hành lá thái nhỏ</li><li>- Hạt nêm, dầu ăn, xì dầu, vừng trắng <br></li></ul></span></span></font></div><div>Cách làm</div>"},{"id":"33a33129-42c1-430e-b2c3-f81d4ffa5375","type":"image","src":"http://images1.afamily.channelvn.net/Images/Uploaded/Share/2011/01/28/mien11.jpg"},{"type":"text","html":"<div><font><span><span><p>Amthuc.com.vn</p></span></span></font></div><font><span><span><p><br></p></span></span></font><div><font><span><span><p>Theo Afamily</p></span></span></font><font><br></font><font><span><span></span></span></font></div><div>Trình bày</div><div> <br></div>"}]
