[{"type":"text","html":"<div> <font style=\"font-family: Arial; font-weight: bold;\" size=\"2\">Món ăn là sự kết hợp măng với thịt gà. Vị măng chua quện với vị ngọt của thịt gà và trứng tạo nên sự thơm ngon của món hấp này.</font> </div><font>Món ăn là sự kết hợp măng với thịt gà. Vị măng chua quện với vị ngọt của thịt gà và trứng tạo nên sự thơm ngon của món hấp này.</font><div>Nguyên liệu</div><p><font>- 1 cây măng củ</font></p><p><font><br></font></p><p><font>- 2 miếng fillet thịt ức gà</font></p><p><font><br></font></p><p><font>- 1 quả trứng gà</font></p><p><font><br></font></p><p><font>- 3 thìa súp hành lá thái nhỏ</font></p><p><font><br></font></p><p><font>- 3 thìa súp rau răm thái nhỏ</font></p><p><font><br></font></p><p><font>- 2 thìa cà phê hạt nêm</font></p><p><font><br></font></p><p><font>- ½ thìa cà phê tiêu</font></p><p><font><br></font></p><p><font>- Hành lá</font></p><p><font><br></font></p><p><font>- Tương ớt</font></p><div>Cách làm</div>"},{"id":"e5cb81f2-0229-4de6-86a8-97fa593af127","type":"image","src":"http://us.24h.com.vn/upload/2-2011/images/2011-06-15/1308105582-am_thuc_24h.jpg"},{"type":"text","html":"<p><font><br></font></p><p><font><br></font></p><p><font>- Măng củ thái lát tròn thật mỏng.</font></p><p><font><br></font></p><p><font><br></font></p>"},{"id":"1e7d6130-4cf7-428e-8495-57b8b4c88aa3","type":"image","src":"http://us.24h.com.vn/upload/2-2011/images/2011-06-15/1308105582-am_thuc_24h2.jpg"},{"type":"text","html":"<p><font><br></font></p><p><font><br></font></p><p><font>- Ức gà xay nhuyễn. Trộn thịt ức gà với trứng, hành lá, rau răm, hạt nêm và tiêu.</font></p><p><br></p><p><font><br></font></p>"},{"id":"1255dbb8-006a-4f80-86b1-bdaa13d14b64","type":"image","src":"http://us.24h.com.vn/upload/2-2011/images/2011-06-15/1308105582-am_thuc_24h3.jpg"},{"type":"text","html":"<p><font><br></font></p><p><font><br></font></p><p><font>- Cuốn nhân thịt gà vào mỗi lát măng, dùng lá hành buộc lại để cố định.</font></p><p><font><br></font></p><br></br>"},{"id":"3c3f6db2-d6a6-4db5-914e-c1c74c384ceb","type":"image","src":"http://us.24h.com.vn/upload/2-2011/images/2011-06-15/1308105582-am_thuc_24h5.jpg"},{"type":"text","html":"<p><font><br></font></p><p><font><br></font></p><p><font>- Xếp những cuốn măng vào chõ hấp khoảng 10-15 phút cho chín.</font></p><p><font><br></font></p><p><font>- Gắp cuốn măng ra đĩa, khi ăn chấm kèm với tương ớt.</font></p><p><font><br></font></p><p><font>Amthuc.com.vn</font></p><p><font><span>Theo linhihi</span><br></font></p><div>Trình bày</div><div> <br></div>"}]
