[{"type":"text","html":"<div> <font style=\"font-family: Arial; font-weight: bold;\" size=\"2\">Thời tiết mùa đông mà có bát canh bò hầm ăn với cơm nóng thì bạn sẽ thấy khỏe hơn rất nhiều đấy. </font> </div><font>Thời tiết mùa đông mà có bát canh bò hầm ăn với cơm nóng thì bạn sẽ thấy khỏe hơn rất nhiều đấy. </font><div>Nguyên liệu</div><p><font>Thịt bò 400g</font></p><p><font>Cà rốt 1 củ</font></p><p><font>- Khoai tây 2 củ</font></p><p><font>- Hành tây nửa củ</font></p><p><font>- Tỏi 1 củ</font></p><p><font>- Rượu vang đỏ ½ chén</font></p><p><font>- Nước xốt cà chua ¾ chén</font></p><p><font>- Hạt nêm</font></p><p><font>- Dầu ăn</font></p><p><font><br></font></p>"},{"id":"6e684bd4-6e51-49b3-a6c9-f910e62775da","type":"image","src":"http://24hn02.24hstatic.com:8008/upload/1-2011/images/2011-01-02/1293932949-bo-ham1---Copy--2-.jpg"},{"type":"text","html":"<div>Cách làm</div><font><strong><br> </strong></font>"},{"id":"83bbdf16-fd76-470d-a1fd-eb70a60e82a7","type":"image","src":"http://24hn02.24hstatic.com:8008/upload/1-2011/images/2011-01-02/1293932949-bo-ham2---Copy.jpg"},{"type":"text","html":"<p><font><br></font></p><p><font>- Thịt bò cắt miếng vuông.</font></p><p><font><br></font></p><p><font>- Khoai tây, cà rốt cạo vỏ thái miếng</font></p><p><font><br></font></p><p><font>- Hành tây xắt miếng vuông</font></p><p><font><br></font></p>"},{"id":"9d36d2c5-5869-4b0f-9caf-72c9f6803bcb","type":"image","src":"http://24hn02.24hstatic.com:8008/upload/1-2011/images/2011-01-02/1293932949-bo-ham3---Copy.jpg"},{"type":"text","html":"<p><font><br></font></p><p><font>- Tỏi bóc vỏ thái lát mỏng</font></p><p><font>- Cho 1 thìa dầu ăn vào chảo đun nóng. Phi tỏi cho thơm.</font></p>"},{"id":"7ef149fd-a985-4a4c-beda-78cba0ca2cb1","type":"image","src":"http://24hn02.24hstatic.com:8008/upload/1-2011/images/2011-01-02/1293932949-bo-ham4.jpg"},{"type":"text","html":"<p><font>- Bỏ thịt bò vào xào, nêm chút hạt nêm cho ngấm.</font> </p>"},{"id":"91ef332b-68c4-475b-9ec0-ab9d9f4f886e","type":"image","src":"http://24hn02.24hstatic.com:8008/upload/1-2011/images/2011-01-02/1293932949-bo-ham5.jpg"},{"type":"text","html":"<p><font>- Khi thịt bò chín tái mặt thì cho khoai tây, cà rốt và hành tây vào xào cùng. Nêm tiếp chút hạt nêm nữa.</font></p><p><font><br></font> </p>"},{"id":"ae3ea774-ae1e-401e-8b70-64bf631a8fc7","type":"image","src":"http://24hn02.24hstatic.com:8008/upload/1-2011/images/2011-01-02/1293932949-bo-ham6.jpg"},{"type":"text","html":"<p><font>- Đảo đều, đun một lúc cho rau củ ngấm.</font></p><p><font><br></font></p>"},{"id":"9f96597d-bc55-487e-a85e-a0aba3165251","type":"image","src":"http://24hn02.24hstatic.com:8008/upload/1-2011/images/2011-01-02/1293932949-bo-ham7.jpg"},{"type":"text","html":"<p><font>- Tiếp đó cho rượu vang đỏ.</font></p>"},{"id":"ea3ebb54-5d86-4d9d-8c4e-ac9175c14929","type":"image","src":"http://24hn02.24hstatic.com:8008/upload/1-2011/images/2011-01-02/1293932949-bo-ham8.jpg"},{"type":"text","html":"<p><font>- Cho xốt cà chua.</font> </p>"},{"id":"5516f863-5550-47fa-8140-4ac8bc4d93e0","type":"image","src":"http://24hn02.24hstatic.com:8008/upload/1-2011/images/2011-01-02/1293932949-bo-ham9.jpg"},{"type":"text","html":"<p><font>- Rồi thêm nước xâm xấp, đun sôi sau đó nhỏ lửa âm ỉ.</font></p><p><font><br></font> </p>"},{"id":"575263ad-ec6d-4586-b135-3d18cea11cfd","type":"image","src":"http://24hn02.24hstatic.com:8008/upload/1-2011/images/2011-01-02/1293932949-bo-ham10.jpg"},{"type":"text","html":"<p><font><br></font></p><p><font>- Nêm nếm lại gia vị cho vừa miệng.</font></p><p><font><br></font></p><p><font>- Hầm đến khi các nguyên liệu chín mềm, canh hơi sanh sánh lại là được. Rắc chút tiêu đen cho thơm rồi tắt bếp.</font></p><p><font><br></font></p>"},{"id":"ce66bcf8-0ffa-4254-8683-3d050b19b0bb","type":"image","src":"http://24hn02.24hstatic.com:8008/upload/1-2011/images/2011-01-02/1293932949-bo-ham---Copy---Copy.jpg"},{"type":"text","html":"<p><font><br></font></p><p><font>- Múc ra bát ăn nóng với bánh mỳ hoặc cơm trắng</font></p><p><br></p><p><font><br></font></p><p><font>Nguồn: 24h</font></p><p><font><span>Amthuc.com.vn/Leo</span><br></font></p><div>Trình bày</div><div> <br></div>"}]
